{
  "publicPath": "/dist/",
  "all": [
    "style/app.79c836751220ba1c6970.css",
    "js/app.79c836751220ba1c6970.js",
    "index.html"
  ],
  "initial": [
    "style/app.79c836751220ba1c6970.css",
    "js/app.79c836751220ba1c6970.js"
  ],
  "async": [],
  "modules": {
    "1ecd9f1d": [
      0,
      1
    ],
    "5393c3bc": [
      0,
      1
    ],
    "6808e5a2": [
      0,
      1
    ],
    "5515a6f4": [
      0,
      1
    ],
    "bc499e18": [
      0,
      1
    ],
    "5b3aaba3": [
      0,
      1
    ],
    "37593cdc": [
      0,
      1
    ],
    "25441bb9": [
      0,
      1
    ],
    "3a1f19d5": [
      0,
      1
    ],
    "3f51fdd5": [
      0,
      1
    ],
    "0796078e": [
      0,
      1
    ],
    "73690d49": [
      0,
      1
    ],
    "011354a4": [
      0,
      1
    ],
    "8cd05a94": [
      0,
      1
    ],
    "1d891c3f": [
      0,
      1
    ],
    "86787f50": [
      0,
      1
    ],
    "12793bdc": [
      0,
      1
    ],
    "82c8c81c": [
      0,
      1
    ],
    "d02bc9b6": [
      0,
      1
    ],
    "bba8fc94": [
      0,
      1
    ],
    "834011e4": [
      0,
      1
    ],
    "a9f5ba48": [
      0,
      1
    ],
    "560d5d90": [
      0,
      1
    ],
    "3cd18736": [
      0,
      1
    ],
    "6d149d3a": [
      0,
      1
    ],
    "3856ef54": [
      0,
      1
    ],
    "b6b6b58a": [
      0,
      1
    ],
    "37716b5a": [
      0,
      1
    ],
    "6c95fd33": [
      0,
      1
    ],
    "796eb6da": [
      0,
      1
    ],
    "03879378": [
      0,
      1
    ],
    "2fad03e3": [
      0,
      1
    ],
    "58b51232": [
      0,
      1
    ],
    "5d4f2589": [
      0,
      1
    ],
    "fa103bec": [
      0,
      1
    ],
    "4f973c55": [
      0,
      1
    ],
    "e15e7f94": [
      0,
      1
    ],
    "6c786f03": [
      0,
      1
    ],
    "15be7108": [
      0,
      1
    ],
    "17333b8e": [
      0,
      1
    ],
    "3a7a351a": [
      0,
      1
    ],
    "bf211918": [
      0,
      1
    ],
    "0ff95243": [
      0,
      1
    ],
    "ce370ec4": [
      0,
      1
    ]
  }
}